planetae_logger.py
planetae_logger-0.3.0.dist-info/LICENSE
planetae_logger-0.3.0.dist-info/WHEEL
planetae_logger-0.3.0.dist-info/METADATA
planetae_logger-0.3.0.dist-info/RECORD
